ffmpeg_normalize/__init__.py
ffmpeg_normalize/__main__.py
ffmpeg_normalize/_cmd_utils.py
ffmpeg_normalize/_errors.py
ffmpeg_normalize/_ffmpeg_normalize.py
ffmpeg_normalize/_logger.py
ffmpeg_normalize/_media_file.py
ffmpeg_normalize/_presets.py
ffmpeg_normalize/_streams.py
ffmpeg_normalize/data/presets/music.json
ffmpeg_normalize/data/presets/podcast.json
ffmpeg_normalize/data/presets/streaming-video.json
ffmpeg_normalize/py.typed
ffmpeg_normalize-1.36.1.dist-info/licenses/LICENSE.md
ffmpeg_normalize-1.36.1.dist-info/WHEEL
ffmpeg_normalize-1.36.1.dist-info/entry_points.txt
ffmpeg_normalize-1.36.1.dist-info/METADATA
ffmpeg_normalize-1.36.1.dist-info/RECORD
