Metadata-Version: 2.4
Name: ffmpeg-normalize
Version: 1.36.1
Summary: Normalize audio via ffmpeg
Keywords: ffmpeg,normalize,audio
Author: Werner Robitza
Author-email: Werner Robitza <werner.robitza@gmail.com>
License-Expression: MIT
License-File: LICENSE.md
Classifier: Development Status :: 5 - Production/Stable
Classifier: Intended Audience :: Developers
Classifier: Topic :: Multimedia :: Sound/Audio
Classifier: Topic :: Multimedia :: Sound/Audio :: Analysis
Classifier: Topic :: Multimedia :: Sound/Audio :: Conversion
Classifier: Natural Language :: English
Classifier: Programming Language :: Python :: 3
Classifier: Programming Language :: Python :: 3.9
Classifier: Programming Language :: Python :: 3.10
Classifier: Programming Language :: Python :: 3.11
Classifier: Programming Language :: Python :: 3.12
Classifier: Programming Language :: Python :: 3.13
Classifier: Programming Language :: Python :: 3.14
Requires-Dist: tqdm>=4.64.1
Requires-Dist: colorama>=0.4.6 ; sys_platform == 'win32'
Requires-Dist: ffmpeg-progress-yield>=1.0.1
Requires-Dist: colorlog==6.7.0
Requires-Dist: mutagen>=1.47.0
Requires-Python: >=3.9
Project-URL: Homepage, https://github.com/slhck/ffmpeg-normalize
Project-URL: Repository, https://github.com/slhck/ffmpeg-normalize
